<goodsinfo>
  <goods>
    <area>Guangzhou</area>
    <catalog>Other</catalog>
    <name>bike</name>
    <description>...</description>
    <username>test1</username>
  </goods>
  <goods>
    <area>Shanghai</area>
    <catalog>Digital</catalog>
    <name>mp3</name>
    <description>It is a good one.</description>
    <username>admin</username>
  </goods>
  <goods>
    <area>Shanghai</area>
    <catalog>Book</catalog>
    <name>Parscal</name>
    <description>parscal</description>
    <username>tom</username>
  </goods>
  <goods>
    <area>Shanghai</area>
    <catalog>Other</catalog>
    <name>Job1</name>
    <description>This is a good job.</description>
    <username>admin</username>
  </goods>
  <goods>
    <area>Shanghai</area>
    <catalog>Digital</catalog>
    <name>Nokia</name>
    <description>It is the version.</description>
    <username>admin</username>
  </goods>
  <goods>
    <area>Shanghai</area>
    <catalog>Book</catalog>
    <name>Software Engineering</name>
    <description>It is the 6 edition, and it's very cheap.</description>
    <username>admin</username>
  </goods>
  <goods>
    <area>Beijing</area>
    <catalog>Other</catalog>
    <name>Bus</name>
    <description>Bus group</description>
    <username>admin</username>
  </goods>
  <goods>
    <area>Beijing</area>
    <catalog>Other</catalog>
    <name>Police</name>
    <description>kkkk</description>
    <username>admin</username>
  </goods>
  <goods>
    <area>Guangzhou</area>
    <catalog>Digital</catalog>
    <name>mp3</name>
    <description>kkkk</description>
    <username>admin</username>
  </goods>
  <goods>
    <area>Guangzhou</area>
    <catalog>Digital</catalog>
    <name>23</name>
    <description>32</description>
    <username>admin</username>
  </goods>
  <goods>
    <area>Guangzhou</area>
    <catalog>Other</catalog>
    <name>aaa</name>
    <description>fasd</description>
    <username>admin</username>
  </goods>
  <goods>
    <area>Shanghai</area>
    <catalog>Book</catalog>
    <name>Bike</name>
    <description>great mounting bike</description>
    <username>admin</username>
  </goods>
  <goods>
    <area>Shanghai</area>
    <catalog>Book</catalog>
    <name>I</name>
    <description>I</description>
    <username>admin</username>
  </goods>
  <goods>
    <area>Beijing</area>
    <catalog>Other</catalog>
    <name>House</name>
    <description>house</description>
    <username>admin</username>
  </goods>
  <goods>
    <area>Shanghai</area>
    <catalog>Digital</catalog>
    <name>cd</name>
    <description>cd</description>
    <username>aa</username>
  </goods>
  <goods>
    <area>Shanghai</area>
    <catalog>Digital</catalog>
    <name>DVD</name>
    <description>ajjdsfaffasdf</description>
    <username>Greg</username>
  </goods>
</goodsinfo>